LightYtSearch/__init__.py
LightYtSearch/cli.py
LightYtSearch/core.py
LightYtSearch/extractors.py
LightYtSearch/filters.py
LightYtSearch/utils.py
LightYtSearch/version.py
lightytsearch-0.3.0.dist-info/licenses/LICENSE
lightytsearch-0.3.0.dist-info/METADATA
lightytsearch-0.3.0.dist-info/WHEEL
lightytsearch-0.3.0.dist-info/entry_points.txt
lightytsearch-0.3.0.dist-info/top_level.txt
lightytsearch-0.3.0.dist-info/RECORD
