Metadata-Version: 2.4
Name: LightYtSearch
Version: 0.3.0
Summary: Lightweight YouTube search scraper without using the official API
Home-page: https://github.com/yourusername/LightYtSearch
Author: Your Name
Classifier: Programming Language :: Python :: 3.9
Classifier: Programming Language :: Python :: 3.10
Classifier: Programming Language :: Python :: 3.11
Classifier: License :: OSI Approved :: MIT License
Classifier: Operating System :: OS Independent
Classifier: Development Status :: 4 - Beta
Classifier: Intended Audience :: Developers
Classifier: Topic :: Internet :: WWW/HTTP :: Indexing/Search
Requires-Python: >=3.9
License-File: LICENSE
Requires-Dist: httpx
Requires-Dist: bs4
Requires-Dist: ua-generator
Dynamic: author
Dynamic: classifier
Dynamic: description
Dynamic: description-content-type
Dynamic: home-page
Dynamic: license-file
Dynamic: requires-dist
Dynamic: requires-python
Dynamic: summary
